.gitignore
.travis.yml
LICENSE
Makefile
README.md
__init__.py
requirements.txt
setup.py
.github/banner.png
dsinternals/Utils.py
dsinternals/__init__.py
dsinternals.egg-info/PKG-INFO
dsinternals.egg-info/SOURCES.txt
dsinternals.egg-info/dependency_links.txt
dsinternals.egg-info/top_level.txt
dsinternals/common/__init__.py
dsinternals/common/adsi/__init__.py
dsinternals/common/azuread/__init__.py
dsinternals/common/cryptography/PrivateKeyEncryptionType.py
dsinternals/common/cryptography/RSAKeyMaterial.py
dsinternals/common/cryptography/SecretEncryptionType.py
dsinternals/common/cryptography/X509Certificate2.py
dsinternals/common/cryptography/__init__.py
dsinternals/common/data/DNWithBinary.py
dsinternals/common/data/InstanceType.py
dsinternals/common/data/__init__.py
dsinternals/common/data/dpapi/DPAPIBackupKeyType.py
dsinternals/common/data/dpapi/RoamedCredentialFlags.py
dsinternals/common/data/dpapi/RoamedCredentialType.py
dsinternals/common/data/dpapi/__init__.py
dsinternals/common/data/hello/CustomKeyInformation.py
dsinternals/common/data/hello/CustomKeyInformationVolumeType.py
dsinternals/common/data/hello/KeyCredential.py
dsinternals/common/data/hello/KeyCredentialEntryType.py
dsinternals/common/data/hello/KeyCredentialVersion.py
dsinternals/common/data/hello/KeyFlags.py
dsinternals/common/data/hello/KeySource.py
dsinternals/common/data/hello/KeyStrength.py
dsinternals/common/data/hello/KeyUsage.py
dsinternals/common/data/hello/VolumeType.py
dsinternals/common/data/hello/__init__.py
dsinternals/common/data/hello/fidoAuthenticatorFlags.py
dsinternals/common/data/hello/fidoCOSE.py
dsinternals/common/data/principals/KerberosKeyType.py
dsinternals/common/data/principals/SamAccountType.py
dsinternals/common/data/principals/UserAccountControl.py
dsinternals/common/data/principals/__init__.py
dsinternals/common/data/schema/AttributeSyntax.py
dsinternals/common/data/schema/__init__.py
dsinternals/common/exceptions/__init__.py
dsinternals/common/extensions/__init__.py
dsinternals/common/interop/__init__.py
dsinternals/common/interop/enums/NetCancelOptions.py
