Metadata-Version: 2.1
Name: dsinternals
Version: 1.2.4
Summary: UNKNOWN
Home-page: http://github.com/p0dalirius/pydsinternals
Author: Podalirius
Author-email: podalirius@protonmail.com
License: GPL2
Platform: UNKNOWN
Classifier: Programming Language :: Python :: 3
Classifier: License :: OSI Approved :: GNU General Public License v2 (GPLv2)
Classifier: Operating System :: OS Independent
Requires-Python: >=3.4
